[
    {
        "zrc20_contract_address": "",
        "asset": "",
        "foreign_chain_id": "7000",
        "decimals": 18,
        "name": "ZetaChain ZETA",
        "symbol": "ZETA",
        "coin_type": "Gas",
        "pyth_price_id": "0xb70656181007f487e392bf0d92e55358e9f0da5da6531c7c4ce7828aa11277fe",
        "canonical": "ZETA"
    },
    {
        "zrc20_contract_address": "0x0327f0660525b15Cdb8f1f5FBF0dD7Cd5Ba182aD",
        "asset": "0xaf88d065e77c8cC2239327C5EDb3A432268e5831",
        "foreign_chain_id": "42161",
        "decimals": 6,
        "name": "ZetaChain ZRC20 USDC on Arbitrum One",
        "symbol": "USDC.ARB",
        "coin_type": "ERC20",
        "gas_limit": "100000",
        "paused": false,
        "liquidity_cap": "750000000000",
        "pyth_price_id": "0xeaa020c61cc479712813461ce153894a96a6c00b21ed0cfc2798d1f9a9e9c94a",
        "canonical": "USDC"
    },
    {
        "zrc20_contract_address": "0x05BA149A7bd6dC1F937fA9046A9e05C05f3b18b0",
        "asset": "0x8AC76a51cc950d9822D68b83fE1Ad97B32Cd580d",
        "foreign_chain_id": "56",
        "decimals": 18,
        "name": "ZetaChain ZRC20 USDC on BSC",
        "symbol": "USDC.BSC",
        "coin_type": "ERC20",
        "gas_limit": "100000",
        "paused": false,
        "liquidity_cap": "1000000000000000000000000",
        "pyth_price_id": "0xeaa020c61cc479712813461ce153894a96a6c00b21ed0cfc2798d1f9a9e9c94a",
        "canonical": "USDC"
    },
    {
        "zrc20_contract_address": "0x0ca762FA958194795320635c11fF0C45C6412958",
        "asset": "0xFd086bC7CD5C481DCC9C85ebE478A1C0b69FCbb9",
        "foreign_chain_id": "42161",
        "decimals": 6,
        "name": "ZetaChain ZRC20 USDT on Arbitrum One",
        "symbol": "USDT.ARB",
        "coin_type": "ERC20",
        "gas_limit": "100000",
        "paused": false,
        "liquidity_cap": "750000000000",
        "pyth_price_id": "0x2b89b9dc8fdf9f34709a5b106b472f0f39bb6ca9ce04b0fd7f2e971688e2e53b",
        "canonical": "USDT"
    },
    {
        "zrc20_contract_address": "0x0cbe0dF132a6c6B4a2974Fa1b7Fb953CF0Cc798a",
        "asset": "0xA0b86991c6218b36c1d19D4a2e9Eb0cE3606eB48",
        "foreign_chain_id": "1",
        "decimals": 6,
        "name": "ZetaChain ZRC20 USDC on ETH",
        "symbol": "USDC.ETH",
        "coin_type": "ERC20",
        "gas_limit": "100000",
        "paused": false,
        "liquidity_cap": "2500000000000",
        "pyth_price_id": "0xeaa020c61cc479712813461ce153894a96a6c00b21ed0cfc2798d1f9a9e9c94a",
        "canonical": "USDC"
    },
    {
        "zrc20_contract_address": "0x13A0c5930C028511Dc02665E7285134B6d11A5f4",
        "asset": "",
        "foreign_chain_id": "8332",
        "decimals": 8,
        "name": "ZetaChain ZRC20 BTC-btc_mainnet",
        "symbol": "BTC.BTC",
        "coin_type": "Gas",
        "gas_limit": "254",
        "paused": false,
        "liquidity_cap": "10000000000",
        "pyth_price_id": "0xe62df6c8b4a85fe1a67db44dc12de5db330f7ac66b72dc658afedf0f4a415b43",
        "canonical": "BTC"
    },
    {
        "zrc20_contract_address": "0x1de70f3e971B62A0707dA18100392af14f7fB677",
        "asset": "",
        "foreign_chain_id": "8453",
        "decimals": 18,
        "name": "ZetaChain ZRC20 Base Mainnet ETH",
        "symbol": "ETH.BASE",
        "coin_type": "Gas",
        "gas_limit": "21000",
        "paused": false,
        "liquidity_cap": "500000000000000000000",
        "pyth_price_id": "0xff61491a931112ddf1bd8147cd1b641375f79f5825126d665480874634fd0ace",
        "canonical": "ETH"
    },
    {
        "zrc20_contract_address": "0x236b0DE675cC8F46AE186897fCCeFe3370C9eDeD",
        "asset": "0x6982508145454Ce325dDbE47a25d4ec3d2311933",
        "foreign_chain_id": "1",
        "decimals": 18,
        "name": "ZetaChain ZRC20 PEPE on ETH",
        "symbol": "PEPE.ETH",
        "coin_type": "ERC20",
        "gas_limit": "100000",
        "paused": false,
        "liquidity_cap": "50000000000000000000000000000",
        "pyth_price_id": "0xd69731a2e74ac1ce884fc3890f7ee324b6deb66147055249568869ed700882e4",
        "canonical": "PEPE"
    },
    {
        "zrc20_contract_address": "0x2Db395976CDb9eeFCc8920F4F2f0736f1D575794",
        "asset": "0x9702230A8Ea53601f5cD2dc00fDBc13d4dF4A8c7",
        "foreign_chain_id": "43114",
        "decimals": 6,
        "name": "ZetaChain ZRC20 USDT on Avalanche C-Chain",
        "symbol": "USDT.AVAX",
        "coin_type": "ERC20",
        "gas_limit": "100000",
        "paused": false,
        "liquidity_cap": "750000000000",
        "pyth_price_id": "0x2b89b9dc8fdf9f34709a5b106b472f0f39bb6ca9ce04b0fd7f2e971688e2e53b",
        "canonical": "USDT"
    },
    {
        "zrc20_contract_address": "0x3e128c169564DD527C8e9bd85124BF6A890E5a5f",
        "asset": "0xcbB7C0000aB88B473b1f5aFd9ef808440eed33Bf",
        "foreign_chain_id": "1",
        "decimals": 8,
        "name": "ZetaChain ZRC20 cbBTC on Ethereum Mainnet",
        "symbol": "CBBTC.ETH",
        "coin_type": "ERC20",
        "gas_limit": "100000",
        "paused": false,
        "liquidity_cap": "1000000000",
        "pyth_price_id": "0x2817d7bfe5c64b8ea956e9a26f573ef64e72e4d7891f2d6af9bcc93f7aff9a97",
        "canonical": "cbBTC"
    },
    {
        "zrc20_contract_address": "0x48f80608B672DC30DC7e3dbBd0343c5F02C738Eb",
        "asset": "",
        "foreign_chain_id": "56",
        "decimals": 18,
        "name": "ZetaChain ZRC20 BNB-bsc_mainnet",
        "symbol": "BNB.BSC",
        "coin_type": "Gas",
        "gas_limit": "21000",
        "paused": false,
        "liquidity_cap": "2000000000000000000000",
        "pyth_price_id": "0x2f95862b045670cd22bee3114c39763a4a08beeb663b145d283c31d7d1101c4f",
        "canonical": "BNB"
    },
    {
        "zrc20_contract_address": "0x4bC32034caCcc9B7e02536945eDbC286bACbA073",
        "asset": "",
        "foreign_chain_id": "900",
        "decimals": 9,
        "name": "ZetaChain ZRC20 SOL on Solana Mainnet",
        "symbol": "SOL.SOL",
        "coin_type": "Gas",
        "gas_limit": "5000",
        "paused": false,
        "liquidity_cap": "3000000000000",
        "pyth_price_id": "0xef0d8b6fda2ceba41da15d4095d1da392a0d2f8ed0c6c7bc0f4cfac8c280b56d",
        "canonical": "SOL"
    },
    {
        "zrc20_contract_address": "0x54Bf2B1E91FCb56853097BD2545750d218E245e1",
        "asset": "cbbtcf3aa214zXHbiAZQwf4122FBYbraNdFqgw4iMij",
        "foreign_chain_id": "900",
        "decimals": 8,
        "name": "ZetaChain ZRC20 cbBTC on Solana Mainnet",
        "symbol": "CBBTC.SOL",
        "coin_type": "ERC20",
        "gas_limit": "100000",
        "paused": false,
        "liquidity_cap": "1000000000",
        "pyth_price_id": "0x2817d7bfe5c64b8ea956e9a26f573ef64e72e4d7891f2d6af9bcc93f7aff9a97",
        "canonical": "cbBTC"
    },
    {
        "zrc20_contract_address": "0x777915D031d1e8144c90D025C594b3b8Bf07a08d",
        "asset": "0x95aD61b0a150d79219dCF64E1E6Cc01f0B64C4cE",
        "foreign_chain_id": "1",
        "decimals": 18,
        "name": "ZetaChain ZRC20 SHIB on ETH",
        "symbol": "SHIB.ETH",
        "coin_type": "ERC20",
        "gas_limit": "100000",
        "paused": false,
        "liquidity_cap": "50000000000000000000000000000",
        "pyth_price_id": "0xf0d57deca57b3da2fe63a493f4c25925fdfd8edf834b20f93e1f84dbd1504d4a",
        "canonical": "SHIB"
    },
    {
        "zrc20_contract_address": "0x7c8dDa80bbBE1254a7aACf3219EBe1481c6E01d7",
        "asset": "0xdAC17F958D2ee523a2206206994597C13D831ec7",
        "foreign_chain_id": "1",
        "decimals": 6,
        "name": "ZetaChain ZRC20 USDT on ETH",
        "symbol": "USDT.ETH",
        "coin_type": "ERC20",
        "gas_limit": "100000",
        "paused": false,
        "liquidity_cap": "2500000000000",
        "pyth_price_id": "0x2b89b9dc8fdf9f34709a5b106b472f0f39bb6ca9ce04b0fd7f2e971688e2e53b",
        "canonical": "USDT"
    },
    {
        "zrc20_contract_address": "0x8344d6f84d26f998fa070BbEA6D2E15E359e2641",
        "asset": "EPjFWdd5AufqSSqeM2qN1xzybapC8G4wEGGkZwyTDt1v",
        "foreign_chain_id": "900",
        "decimals": 6,
        "name": "ZetaChain ZRC20 USDC on Solana Mainnet",
        "symbol": "USDC.SOL",
        "coin_type": "ERC20",
        "gas_limit": "100000",
        "paused": false,
        "liquidity_cap": "1000000000000",
        "pyth_price_id": "0xeaa020c61cc479712813461ce153894a96a6c00b21ed0cfc2798d1f9a9e9c94a",
        "canonical": "USDC"
    },
    {
        "zrc20_contract_address": "0x91d4F0D54090Df2D81e834c3c8CE71C6c865e79F",
        "asset": "0x55d398326f99059fF775485246999027B3197955",
        "foreign_chain_id": "56",
        "decimals": 18,
        "name": "ZetaChain ZRC20 USDT on BSC",
        "symbol": "USDT.BSC",
        "coin_type": "ERC20",
        "gas_limit": "100000",
        "paused": false,
        "liquidity_cap": "1000000000000000000000000",
        "pyth_price_id": "0x2b89b9dc8fdf9f34709a5b106b472f0f39bb6ca9ce04b0fd7f2e971688e2e53b",
        "canonical": "USDT"
    },
    {
        "zrc20_contract_address": "0x96152E6180E085FA57c7708e18AF8F05e37B479D",
        "asset": "0x833589fCD6eDb6E08f4c7C32D4f71b54bdA02913",
        "foreign_chain_id": "8453",
        "decimals": 6,
        "name": "ZetaChain ZRC20 USDC on BASE",
        "symbol": "USDC.BASE",
        "coin_type": "ERC20",
        "gas_limit": "100000",
        "paused": false,
        "liquidity_cap": "1000000000000",
        "pyth_price_id": "0xeaa020c61cc479712813461ce153894a96a6c00b21ed0cfc2798d1f9a9e9c94a",
        "canonical": "USDC"
    },
    {
        "zrc20_contract_address": "0xA614Aebf7924A3Eb4D066aDCA5595E4980407f1d",
        "asset": "",
        "foreign_chain_id": "42161",
        "decimals": 18,
        "name": "ZetaChain ZRC20 Arbitrum One ETH",
        "symbol": "ETH.ARB",
        "coin_type": "Gas",
        "gas_limit": "21000",
        "paused": false,
        "liquidity_cap": "250000000000000000000",
        "pyth_price_id": "0xff61491a931112ddf1bd8147cd1b641375f79f5825126d665480874634fd0ace",
        "canonical": "ETH"
    },
    {
        "zrc20_contract_address": "0xADF73ebA3Ebaa7254E859549A44c74eF7cff7501",
        "asset": "",
        "foreign_chain_id": "137",
        "decimals": 18,
        "name": "ZetaChain ZRC20 Polygon POL-polygon_mainnet",
        "symbol": "POL.POLYGON",
        "coin_type": "Gas",
        "gas_limit": "21000",
        "paused": false,
        "liquidity_cap": "1000000000000000000000000",
        "pyth_price_id": "0xffd11c5a1cfd42f80afb2df4d9f264c15f956d68153335374ec10722edd70472",
        "canonical": "POL"
    },
    {
        "zrc20_contract_address": "0xE80e3e8Ac1C19c744d4c2147172489BEAF23E3C5",
        "asset": "0xcbB7C0000aB88B473b1f5aFd9ef808440eed33Bf",
        "foreign_chain_id": "8453",
        "decimals": 8,
        "name": "ZetaChain ZRC20 cbBTC on Base Mainnet",
        "symbol": "CBBTC.BASE",
        "coin_type": "ERC20",
        "gas_limit": "100000",
        "paused": false,
        "liquidity_cap": "1000000000",
        "pyth_price_id": "0x2817d7bfe5c64b8ea956e9a26f573ef64e72e4d7891f2d6af9bcc93f7aff9a97",
        "canonical": "cbBTC"
    },
    {
        "zrc20_contract_address": "0xE8d7796535F1cd63F0fe8D631E68eACe6839869B",
        "asset": "",
        "foreign_chain_id": "43114",
        "decimals": 18,
        "name": "ZetaChain ZRC20 Avalanche C-Chain AVAX",
        "symbol": "AVAX.AVAX",
        "coin_type": "Gas",
        "gas_limit": "21000",
        "paused": false,
        "liquidity_cap": "20000000000000000000000",
        "pyth_price_id": "0x93da3352f9f1d105fdfe4971cfa80e9dd777bfc5d0f683ebb6e1294b92137bb7",
        "canonical": "AVAX"
    },
    {
        "zrc20_contract_address": "0xEe9CC614D03e7Dbe994b514079f4914a605B4719",
        "asset": "Es9vMFrzaCERmJfrF4H2FYD4KCoNkY11McCe8BenwNYB",
        "foreign_chain_id": "900",
        "decimals": 6,
        "name": "ZetaChain ZRC20 USDT on Solana Mainnet",
        "symbol": "USDT.SOL",
        "coin_type": "ERC20",
        "gas_limit": "100000",
        "paused": false,
        "liquidity_cap": "1000000000000",
        "pyth_price_id": "0x2b89b9dc8fdf9f34709a5b106b472f0f39bb6ca9ce04b0fd7f2e971688e2e53b",
        "canonical": "USDT"
    },
    {
        "zrc20_contract_address": "0xa52Ad01A1d62b408fFe06C2467439251da61E4a9",
        "asset": "0xB97EF9Ef8734C71904D8002F8b6Bc66Dd9c48a6E",
        "foreign_chain_id": "43114",
        "decimals": 6,
        "name": "ZetaChain ZRC20 USDC on Avalanche C-Chain",
        "symbol": "USDC.AVAX",
        "coin_type": "ERC20",
        "gas_limit": "100000",
        "paused": false,
        "liquidity_cap": "750000000000",
        "pyth_price_id": "0x2b89b9dc8fdf9f34709a5b106b472f0f39bb6ca9ce04b0fd7f2e971688e2e53b",
        "canonical": "USDC"
    },
    {
        "zrc20_contract_address": "0xcC683A782f4B30c138787CB5576a86AF66fdc31d",
        "asset": "0x6B175474E89094C44Da98b954EedeAC495271d0F",
        "foreign_chain_id": "1",
        "decimals": 18,
        "name": "ZetaChain ZRC20 DAI on ETH",
        "symbol": "DAI.ETH",
        "coin_type": "ERC20",
        "gas_limit": "100000",
        "paused": false,
        "liquidity_cap": "500000000000000000000000",
        "pyth_price_id": "0xb0948a5e5313200c632b51bb5ca32f6de0d36e9950a942d19751e833f70dabfd",
        "canonical": "DAI"
    },
    {
        "zrc20_contract_address": "0xd0eFed75622e7AA4555EE44F296dA3744E3ceE19",
        "asset": "0x2260FAC5E5542a773Aa44fBCfeDf7C193bc2C599",
        "foreign_chain_id": "1",
        "decimals": 8,
        "name": "ZetaChain ZRC20 WBTC on Ethereum Mainnet",
        "symbol": "WBTC.ETH",
        "coin_type": "ERC20",
        "gas_limit": "100000",
        "paused": false,
        "liquidity_cap": "1000000000",
        "pyth_price_id": "0xc9d8b075a5c69303365ae23633d4e085199bf5c520a3b90fed1322a0342ffc33",
        "canonical": "wBTC"
    },
    {
        "zrc20_contract_address": "0xd97B1de3619ed2c6BEb3860147E30cA8A7dC9891",
        "asset": "",
        "foreign_chain_id": "1",
        "decimals": 18,
        "name": "ZetaChain ZRC20 ETH-eth_mainnet",
        "symbol": "ETH.ETH",
        "coin_type": "Gas",
        "gas_limit": "21000",
        "paused": false,
        "liquidity_cap": "1000000000000000000000",
        "pyth_price_id": "0xff61491a931112ddf1bd8147cd1b641375f79f5825126d665480874634fd0ace",
        "canonical": "ETH"
    },
    {
        "zrc20_contract_address": "0xdbfF6471a79E5374d771922F2194eccc42210B9F",
        "asset": "0xc2132D05D31c914a87C6611C10748AEb04B58e8F",
        "foreign_chain_id": "137",
        "decimals": 6,
        "name": "ZetaChain ZRC20 USDT on POL",
        "symbol": "USDT.POL",
        "coin_type": "ERC20",
        "gas_limit": "100000",
        "paused": false,
        "liquidity_cap": "1000000000000",
        "pyth_price_id": "0x2b89b9dc8fdf9f34709a5b106b472f0f39bb6ca9ce04b0fd7f2e971688e2e53b",
        "canonical": "USDT"
    },
    {
        "zrc20_contract_address": "0xfC9201f4116aE6b054722E10b98D904829b469c3",
        "asset": "0x3c499c542cEF5E3811e1192ce70d8cC03d5c3359",
        "foreign_chain_id": "137",
        "decimals": 6,
        "name": "ZetaChain ZRC20 USDC on POL",
        "symbol": "USDC.POL",
        "coin_type": "ERC20",
        "gas_limit": "100000",
        "paused": false,
        "liquidity_cap": "1000000000000",
        "pyth_price_id": "0xeaa020c61cc479712813461ce153894a96a6c00b21ed0cfc2798d1f9a9e9c94a",
        "canonical": "USDC"
    }
]